{
  "name": "Panama",
  "flag": "🇵🇦",
  "group": "L",
  "manager": "Thomas Christiansen",
  "players": [
    { "number": 1, "name": "Luis Ricardo Mejía", "pos": "GR", "club": "Club Nacional", "born": "1991-03-16" },
    { "number": 2, "name": "César Blackman", "pos": "DEF", "club": "ŠK Slovan Bratislava", "born": "1998-04-02" },
    { "number": 3, "name": "José Córdoba", "pos": "DEF", "club": "Norwich City FC", "born": "2001-06-03" },
    { "number": 4, "name": "Fidel Escobar", "pos": "DEF", "club": "Deportivo Saprissa", "born": "1995-11-09" },
    { "number": 5, "name": "Edgardo Fariña", "pos": "DEF", "club": "FC Pari Nizhny Novgorod", "born": "2001-10-19" },
    { "number": 6, "name": "Cristian Martínez", "pos": "MED", "club": "Hapoel Kiryat Shmona", "born": "1997-06-06" },
    { "number": 7, "name": "José Luis Rodríguez", "pos": "MED", "club": "FC Juárez", "born": "1998-06-19" },
    { "number": 8, "name": "Adalberto Carrasquilla", "pos": "MED", "club": "Pumas UNAM", "born": "1998-11-28" },
    { "number": 9, "name": "Tomás Rodríguez", "pos": "AV", "club": "Deportivo Saprissa", "born": "1999-03-09" },
    { "number": 10, "name": "Ismael Díaz", "pos": "MED", "club": "Club León", "born": "1997-05-12" },
    { "number": 11, "name": "Yoel Bárcenas", "pos": "MED", "club": "Mazatlán FC", "born": "1993-10-23" },
    { "number": 12, "name": "César Samudio", "pos": "GR", "club": "CD Marathón", "born": "1994-12-23" },
    { "number": 13, "name": "Yovani Ramos", "pos": "DEF", "club": "Puerto Cabello FC", "born": "1997-11-26" },
    { "number": 14, "name": "Carlos Harvey", "pos": "DEF", "club": "Minnesota United FC", "born": "2000-02-03" },
    { "number": 15, "name": "Éric Davis", "pos": "DEF", "club": "CD Plaza Amador", "born": "1991-03-31" },
    { "number": 16, "name": "Andrés Andrade", "pos": "DEF", "club": "LASK Linz", "born": "1998-10-16" },
    { "number": 17, "name": "José Fajardo", "pos": "AV", "club": "CD Universidad Católica", "born": "1993-08-18" },
    { "number": 18, "name": "Cecilio Waterman", "pos": "AV", "club": "CD Universidad de Concepción", "born": "1991-04-13" },
    { "number": 19, "name": "Alberto Quintero", "pos": "MED", "club": "CD Plaza Amador", "born": "1987-12-18" },
    { "number": 20, "name": "Aníbal Godoy", "pos": "MED", "club": "San Diego FC", "born": "1990-02-10" },
    { "number": 21, "name": "César Yanis", "pos": "MED", "club": "CD Cobresal", "born": "1996-11-28" },
    { "number": 22, "name": "Orlando Mosquera", "pos": "GR", "club": "Al Fayha FC", "born": "1994-07-25" },
    { "number": 23, "name": "Amir Murillo", "pos": "DEF", "club": "Beşiktaş JK", "born": "1996-12-11" },
    { "number": 24, "name": "Azarías Londoño", "pos": "AV", "club": "CD Universidad Católica", "born": "2001-06-21" },
    { "number": 25, "name": "Roderick Miller", "pos": "DEF", "club": "Turan Tovuz", "born": "1992-04-03" },
    { "number": 26, "name": "Jorge Gutiérrez", "pos": "DEF", "club": "Deportivo La Guaira", "born": "1998-09-01" }
  ]
}